ControlPlaneAPI/__init__.py
ControlPlaneAPI/api_client.py
ControlPlaneAPI/api_response.py
ControlPlaneAPI/configuration.py
ControlPlaneAPI/exceptions.py
ControlPlaneAPI/py.typed
ControlPlaneAPI/rest.py
ControlPlaneAPI/api/__init__.py
ControlPlaneAPI/api/node_creation_api.py
ControlPlaneAPI/api/orchestrate_api.py
ControlPlaneAPI/models/__init__.py
ControlPlaneAPI/models/dummy.py
ControlPlaneAPI/models/put_configure_request.py
ControlPlaneAPI/models/put_configure_request_components_inner.py
ControlPlaneAPI/models/put_configure_request_components_inner_io_handles.py
ControlPlaneAPI/models/put_configure_request_components_inner_io_handles_input_inner.py
controlplaneapi-1.6.1.dist-info/METADATA
controlplaneapi-1.6.1.dist-info/WHEEL
controlplaneapi-1.6.1.dist-info/top_level.txt
controlplaneapi-1.6.1.dist-info/RECORD
