Metadata-Version: 2.4
Name: ControlPlaneAPI
Version: 1.6.1
Summary: ControlPlaneAPI
Home-page: 
Author: Luke Brown
Author-email: luke.brown@3adesign.co.uk
Keywords: OpenAPI,OpenAPI-Generator,ControlPlaneAPI
Requires-Dist: urllib3<3.0.0,>=1.25.3
Requires-Dist: python-dateutil>=2.8.2
Requires-Dist: pydantic>=2
Requires-Dist: typing-extensions>=4.7.1
Dynamic: author
Dynamic: author-email
Dynamic: description
Dynamic: description-content-type
Dynamic: keywords
Dynamic: requires-dist
Dynamic: summary
